modules_cicd/__init__.py
modules_cicd/src/__init__.py
modules_cicd/src/classes/Repository.py
modules_cicd/src/classes/Suppliers.py
modules_cicd/src/classes/TypeProjectEnum.py
modules_cicd/src/classes/__init__.py
modules_cicd/src/classes/dataClass.py
modules_cicd/src/interfaces/CICDService.py
modules_cicd/src/interfaces/Repository.py
modules_cicd/src/interfaces/__init__.py
modules_cicd/src/service/__init__.py
modules_cicd/src/service/src/__init__.py
modules_cicd/src/service/src/Interfaces/__init__.py
modules_cicd/src/service/src/Interfaces/git.py
modules_cicd/src/service/src/Interfaces/interfaces.py
modules_cicd/src/service/src/classes/__init__.py
modules_cicd/src/service/src/classes/dataClass.py
modules_cicd/src/service/src/classes/github.py
modules_cicd/src/service/src/classes/gitlab.py
modules_cicd/src/service/src/classes/jenkinsAPI.py
modules_cicd/src/service/src/classes/vercelAPI.py
modules_cicd/src/service/test/__init__.py
modules_cicd/src/service/test/test_api_vercel.py
modules_cicd/src/service/test/test_github.py
modules_cicd/src/service/test/test_gitlab.py
modules_cicd/src/service/test/test_xml_jenkins.py
modules_cicd/test/__init__.py
modules_cicd-1.22.4.dist-info/METADATA
modules_cicd-1.22.4.dist-info/WHEEL
modules_cicd-1.22.4.dist-info/top_level.txt
modules_cicd-1.22.4.dist-info/RECORD
