Metadata-Version: 2.1
Name: modules-cicd
Version: 1.22.4
Summary: Testing installation of Package
Home-page: UNKNOWN
Author: auth
Author-email: author@email.com
License: MIT
Platform: UNKNOWN
